msgqywx/__init__.py
msgqywx/msgqywx.py
msgqywx-0.7.0.dist-info/LICENSE
msgqywx-0.7.0.dist-info/METADATA
msgqywx-0.7.0.dist-info/WHEEL
msgqywx-0.7.0.dist-info/top_level.txt
msgqywx-0.7.0.dist-info/RECORD
