Metadata-Version: 2.1
Name: msgqywx
Version: 0.7.0
Summary: 发送企业微信应用消息
Home-page: https://github.com/veink-y/msgqywx
Author: demon finch
Author-email: yhf2lj@outlook.com
License: MIT
Keywords: 企业微信 消息
License-File: LICENSE
Requires-Dist: requests
